skcvideo/__init__.py
skcvideo/button_widget.py
skcvideo/chatbox.py
skcvideo/colormap.py
skcvideo/colors.py
skcvideo/controlled_fps_video_capture.py
skcvideo/core.py
skcvideo/field_model.py
skcvideo/images_list_incrustation.py
skcvideo/list.py
skcvideo/minimap.py
skcvideo/plot.py
skcvideo/table.py
skcvideo/timeline.py
skcvideo/utils.py
skcvideo/video_capture.py
skcvideo/video_incrustation.py
skcvideo-2.2.3.dist-info/METADATA
skcvideo-2.2.3.dist-info/WHEEL
skcvideo-2.2.3.dist-info/licenses/LICENSE
skcvideo-2.2.3.dist-info/RECORD
