Metadata-Version: 2.4
Name: skcvideo
Version: 2.2.3
Summary: video utils
License-Expression: MIT
License-File: LICENSE
Requires-Python: <3.12,>=3.9
Requires-Dist: click>=8.1.7
Requires-Dist: ffmphisdp==2.5.2
Requires-Dist: imageio-ffmpeg>=0.5.1
Requires-Dist: imageio>=2.30.0
Requires-Dist: numpy<2,>=1.18.5
Requires-Dist: opencv-python>=4.4.0.46
